{
  "date" : "Fri, 04 Aug, 2023 13:08:43 +0000",
  "doco" : "For each file: start is seconds after start activity occurred. Length = milliseconds activity took",
  "files" : [
    {
      "name" : "/fsh-generated/resources/ImplementationGuide-ans.fhir.fr.agenda.json",
      "size" : 7482,
      "processes" : [
        {
          "activity" : "load",
          "start" : 41,
          "length" : 504
        },
        {
          "activity" : "checkR4R4B",
          "start" : 62,
          "length" : 5
        },
        {
          "activity" : "generateNarratives",
          "start" : 62,
          "length" : 538
        },
        {
          "activity" : "validate",
          "start" : 98,
          "length" : 1136
        },
        {
          "activity" : "scanForUsageStats",
          "start" : 99,
          "length" : 1
        },
        {
          "activity" : "validate",
          "start" : 100,
          "length" : 1
        },
        {
          "activity" : "generate1",
          "start" : 101,
          "length" : 268
        },
        {
          "activity" : "generate2",
          "start" : 111,
          "length" : 277
        },
        {
          "activity" : "generateExampleZip",
          "start" : 141,
          "length" : 1
        },
        {
          "activity" : "generateValidationPack",
          "start" : 141,
          "length" : 3
        }
      ]
    },
    {
      "name" : "fsh-generated/resources/CapabilityStatement-GAP-GestionnaireAgenda.json",
      "size" : 9866,
      "processes" : [
        {
          "activity" : "loadResources",
          "start" : 37,
          "length" : 32
        },
        {
          "activity" : "load-configure",
          "start" : 39,
          "length" : 1
        },
        {
          "activity" : "load",
          "start" : 41,
          "length" : 28
        },
        {
          "activity" : "checkR4R4B",
          "start" : 62,
          "length" : 1
        },
        {
          "activity" : "generateNarratives",
          "start" : 63,
          "length" : 44
        },
        {
          "activity" : "validate",
          "start" : 98,
          "length" : 257
        },
        {
          "activity" : "scanForUsageStats",
          "start" : 99,
          "length" : 1
        },
        {
          "activity" : "generate1",
          "start" : 101,
          "length" : 49
        },
        {
          "activity" : "generate2",
          "start" : 112,
          "length" : 126
        },
        {
          "activity" : "generateValidationPack",
          "start" : 141,
          "length" : 1
        },
        {
          "activity" : "scanExamplesForR5",
          "start" : 164,
          "length" : 1
        }
      ]
    },
    {
      "name" : "fsh-generated/resources/SearchParameter-GAP-Appointment-priority.json",
      "size" : 511,
      "processes" : [
        {
          "activity" : "loadResources",
          "start" : 37,
          "length" : 11
        },
        {
          "activity" : "load",
          "start" : 41,
          "length" : 15
        },
        {
          "activity" : "load",
          "start" : 42,
          "length" : 4
        },
        {
          "activity" : "generateNarratives",
          "start" : 63,
          "length" : 14
        },
        {
          "activity" : "validate",
          "start" : 98,
          "length" : 23
        },
        {
          "activity" : "generate1",
          "start" : 101,
          "length" : 7
        },
        {
          "activity" : "generate2",
          "start" : 112,
          "length" : 21
        },
        {
          "activity" : "generateValidationPack",
          "start" : 141,
          "length" : 1
        }
      ]
    },
    {
      "name" : "fsh-generated/resources/CapabilityStatement-GAP-Consommateur.json",
      "size" : 16662,
      "processes" : [
        {
          "activity" : "loadResources",
          "start" : 37,
          "length" : 29
        },
        {
          "activity" : "load",
          "start" : 41,
          "length" : 25
        },
        {
          "activity" : "checkR4R4B",
          "start" : 62,
          "length" : 2
        },
        {
          "activity" : "generateNarratives",
          "start" : 63,
          "length" : 34
        },
        {
          "activity" : "validate",
          "start" : 98,
          "length" : 124
        },
        {
          "activity" : "generate1",
          "start" : 101,
          "length" : 57
        },
        {
          "activity" : "generate2",
          "start" : 112,
          "length" : 77
        },
        {
          "activity" : "generateValidationPack",
          "start" : 141,
          "length" : 5
        }
      ]
    },
    {
      "name" : "fsh-generated/resources/SearchParameter-GAP-Slot-earliestStart.json",
      "size" : 620,
      "processes" : [
        {
          "activity" : "loadResources",
          "start" : 37,
          "length" : 10
        },
        {
          "activity" : "load",
          "start" : 41,
          "length" : 6
        },
        {
          "activity" : "load",
          "start" : 42,
          "length" : 5
        },
        {
          "activity" : "generateNarratives",
          "start" : 63,
          "length" : 13
        },
        {
          "activity" : "validate",
          "start" : 98,
          "length" : 13
        },
        {
          "activity" : "generate1",
          "start" : 101,
          "length" : 7
        },
        {
          "activity" : "generate2",
          "start" : 112,
          "length" : 21
        },
        {
          "activity" : "generateValidationPack",
          "start" : 141,
          "length" : 1
        }
      ]
    },
    {
      "name" : "fsh-generated/resources/CapabilityStatement-GAP-DeclarantRDV.json",
      "size" : 1635,
      "processes" : [
        {
          "activity" : "loadResources",
          "start" : 37,
          "length" : 12
        },
        {
          "activity" : "load",
          "start" : 41,
          "length" : 7
        },
        {
          "activity" : "generateNarratives",
          "start" : 63,
          "length" : 15
        },
        {
          "activity" : "validate",
          "start" : 98,
          "length" : 12
        },
        {
          "activity" : "generate1",
          "start" : 101,
          "length" : 11
        },
        {
          "activity" : "generate2",
          "start" : 112,
          "length" : 12
        }
      ]
    },
    {
      "name" : "fsh-generated/resources/SearchParameter-GAP-Appointment-created.json",
      "size" : 415,
      "processes" : [
        {
          "activity" : "loadResources",
          "start" : 37,
          "length" : 10
        },
        {
          "activity" : "load-configure",
          "start" : 39,
          "length" : 1
        },
        {
          "activity" : "load",
          "start" : 41,
          "length" : 4
        },
        {
          "activity" : "load",
          "start" : 42,
          "length" : 4
        },
        {
          "activity" : "generateNarratives",
          "start" : 63,
          "length" : 13
        },
        {
          "activity" : "validate",
          "start" : 98,
          "length" : 6
        },
        {
          "activity" : "loadLists",
          "start" : 99,
          "length" : 1
        },
        {
          "activity" : "generate1",
          "start" : 101,
          "length" : 6
        },
        {
          "activity" : "generate2",
          "start" : 112,
          "length" : 20
        }
      ]
    },
    {
      "name" : "fsh-generated/resources/SearchParameter-GAP-Appointment-description.json",
      "size" : 586,
      "processes" : [
        {
          "activity" : "loadResources",
          "start" : 37,
          "length" : 11
        },
        {
          "activity" : "load",
          "start" : 41,
          "length" : 5
        },
        {
          "activity" : "load",
          "start" : 42,
          "length" : 4
        },
        {
          "activity" : "generateNarratives",
          "start" : 63,
          "length" : 13
        },
        {
          "activity" : "validate",
          "start" : 98,
          "length" : 7
        },
        {
          "activity" : "generate1",
          "start" : 101,
          "length" : 6
        },
        {
          "activity" : "generate2",
          "start" : 112,
          "length" : 22
        },
        {
          "activity" : "generateValidationPack",
          "start" : 141,
          "length" : 1
        }
      ]
    },
    {
      "name" : "fsh-generated/resources/StructureDefinition-gap-bundle-reponse-demande-consult-dispo.json",
      "size" : 10802,
      "processes" : [
        {
          "activity" : "loadResources",
          "start" : 37,
          "length" : 945
        },
        {
          "activity" : "load",
          "start" : 39,
          "length" : 987
        },
        {
          "activity" : "generateSnapshots",
          "start" : 42,
          "length" : 9734
        },
        {
          "activity" : "generateNarratives",
          "start" : 63,
          "length" : 9323
        },
        {
          "activity" : "validate",
          "start" : 83,
          "length" : 9334
        },
        {
          "activity" : "checkConformanceResources",
          "start" : 99,
          "length" : 3
        },
        {
          "activity" : "scanForUsageStats",
          "start" : 99,
          "length" : 7
        },
        {
          "activity" : "generate1",
          "start" : 101,
          "length" : 2376
        },
        {
          "activity" : "generate2",
          "start" : 112,
          "length" : 8158
        },
        {
          "activity" : "generateValidationPack",
          "start" : 141,
          "length" : 69
        },
        {
          "activity" : "scanProfilesForR5",
          "start" : 164,
          "length" : 1
        },
        {
          "activity" : "scanExamplesForR5",
          "start" : 164,
          "length" : 4
        }
      ]
    },
    {
      "name" : "fsh-generated/resources/SearchParameter-GAP-Appointment-latestStart.json",
      "size" : 652,
      "processes" : [
        {
          "activity" : "loadResources",
          "start" : 38,
          "length" : 11
        },
        {
          "activity" : "scan",
          "start" : 39,
          "length" : 1
        },
        {
          "activity" : "load",
          "start" : 41,
          "length" : 4
        },
        {
          "activity" : "load",
          "start" : 42,
          "length" : 4
        },
        {
          "activity" : "generateNarratives",
          "start" : 72,
          "length" : 19
        },
        {
          "activity" : "validate",
          "start" : 98,
          "length" : 112
        },
        {
          "activity" : "scanForUsageStats",
          "start" : 100,
          "length" : 1
        },
        {
          "activity" : "generate1",
          "start" : 103,
          "length" : 8
        },
        {
          "activity" : "generate2",
          "start" : 120,
          "length" : 21
        },
        {
          "activity" : "generateValidationPack",
          "start" : 141,
          "length" : 2
        }
      ]
    },
    {
      "name" : "fsh-generated/resources/SearchParameter-GAP-Slot-latestStart.json",
      "size" : 612,
      "processes" : [
        {
          "activity" : "loadResources",
          "start" : 38,
          "length" : 11
        },
        {
          "activity" : "load",
          "start" : 41,
          "length" : 5
        },
        {
          "activity" : "load",
          "start" : 42,
          "length" : 4
        },
        {
          "activity" : "generateNarratives",
          "start" : 72,
          "length" : 13
        },
        {
          "activity" : "validate",
          "start" : 98,
          "length" : 14
        },
        {
          "activity" : "generate1",
          "start" : 103,
          "length" : 6
        },
        {
          "activity" : "generate2",
          "start" : 120,
          "length" : 12
        },
        {
          "activity" : "scanExamplesForR5",
          "start" : 164,
          "length" : 1
        }
      ]
    },
    {
      "name" : "fsh-generated/resources/Slot-example.json",
      "size" : 915,
      "processes" : [
        {
          "activity" : "loadResources",
          "start" : 38,
          "length" : 12
        },
        {
          "activity" : "generateNarratives",
          "start" : 72,
          "length" : 50
        },
        {
          "activity" : "validate",
          "start" : 100,
          "length" : 114
        },
        {
          "activity" : "generate1",
          "start" : 103,
          "length" : 9
        },
        {
          "activity" : "generate2",
          "start" : 120,
          "length" : 13
        }
      ]
    },
    {
      "name" : "fsh-generated/resources/StructureDefinition-gap-bundle-reponse-demande-consult-rdv.json",
      "size" : 11405,
      "processes" : [
        {
          "activity" : "loadResources",
          "start" : 38,
          "length" : 1028
        },
        {
          "activity" : "load",
          "start" : 40,
          "length" : 1033
        },
        {
          "activity" : "generateSnapshots",
          "start" : 52,
          "length" : 10283
        },
        {
          "activity" : "checkR4R4B",
          "start" : 62,
          "length" : 1
        },
        {
          "activity" : "generateNarratives",
          "start" : 72,
          "length" : 10280
        },
        {
          "activity" : "validate",
          "start" : 92,
          "length" : 5274
        },
        {
          "activity" : "scanForUsageStats",
          "start" : 100,
          "length" : 5
        },
        {
          "activity" : "generate1",
          "start" : 103,
          "length" : 2364
        },
        {
          "activity" : "generate2",
          "start" : 120,
          "length" : 5714
        },
        {
          "activity" : "generateValidationPack",
          "start" : 141,
          "length" : 78
        },
        {
          "activity" : "scanExamplesForR5",
          "start" : 164,
          "length" : 4
        }
      ]
    },
    {
      "name" : "fsh-generated/resources/Schedule-example.json",
      "size" : 2304,
      "processes" : [
        {
          "activity" : "loadResources",
          "start" : 39,
          "length" : 31
        },
        {
          "activity" : "generateNarratives",
          "start" : 82,
          "length" : 565
        },
        {
          "activity" : "validate",
          "start" : 100,
          "length" : 289
        },
        {
          "activity" : "generate1",
          "start" : 106,
          "length" : 17
        },
        {
          "activity" : "generate2",
          "start" : 126,
          "length" : 19
        }
      ]
    },
    {
      "name" : "fsh-generated/resources/CapabilityStatement-Gap-Declarant.json",
      "size" : 5037,
      "processes" : [
        {
          "activity" : "loadResources",
          "start" : 39,
          "length" : 10
        },
        {
          "activity" : "load-configure",
          "start" : 39,
          "length" : 1
        },
        {
          "activity" : "load",
          "start" : 41,
          "length" : 12
        },
        {
          "activity" : "generateNarratives",
          "start" : 83,
          "length" : 25
        },
        {
          "activity" : "validate",
          "start" : 98,
          "length" : 31
        },
        {
          "activity" : "generate1",
          "start" : 106,
          "length" : 25
        },
        {
          "activity" : "generate2",
          "start" : 126,
          "length" : 15
        },
        {
          "activity" : "generateValidationPack",
          "start" : 141,
          "length" : 1
        }
      ]
    },
    {
      "name" : "fsh-generated/resources/CapabilityStatement-GAP-GestionnaireRessources.json",
      "size" : 4121,
      "processes" : [
        {
          "activity" : "loadResources",
          "start" : 39,
          "length" : 9
        },
        {
          "activity" : "load",
          "start" : 41,
          "length" : 10
        },
        {
          "activity" : "checkR4R4B",
          "start" : 62,
          "length" : 1
        },
        {
          "activity" : "generateNarratives",
          "start" : 83,
          "length" : 22
        },
        {
          "activity" : "validate",
          "start" : 98,
          "length" : 26
        },
        {
          "activity" : "generate1",
          "start" : 106,
          "length" : 21
        },
        {
          "activity" : "generate2",
          "start" : 126,
          "length" : 15
        },
        {
          "activity" : "generateValidationPack",
          "start" : 141,
          "length" : 1
        }
      ]
    },
    {
      "name" : "fsh-generated/resources/Appointment-example-req-appointment.json",
      "size" : 1891,
      "processes" : [
        {
          "activity" : "loadResources",
          "start" : 39,
          "length" : 10
        },
        {
          "activity" : "generateNarratives",
          "start" : 83,
          "length" : 50
        },
        {
          "activity" : "validate",
          "start" : 100,
          "length" : 60
        },
        {
          "activity" : "generate1",
          "start" : 106,
          "length" : 15
        },
        {
          "activity" : "generate2",
          "start" : 126,
          "length" : 20
        }
      ]
    },
    {
      "name" : "fsh-generated/resources/SearchParameter-GAP-Appointment-earliestStart.json",
      "size" : 680,
      "processes" : [
        {
          "activity" : "loadResources",
          "start" : 39,
          "length" : 3
        },
        {
          "activity" : "load",
          "start" : 41,
          "length" : 5
        },
        {
          "activity" : "load",
          "start" : 42,
          "length" : 4
        },
        {
          "activity" : "generateNarratives",
          "start" : 83,
          "length" : 13
        },
        {
          "activity" : "validate",
          "start" : 98,
          "length" : 10
        },
        {
          "activity" : "generate1",
          "start" : 106,
          "length" : 6
        },
        {
          "activity" : "generate2",
          "start" : 126,
          "length" : 14
        },
        {
          "activity" : "generateValidationPack",
          "start" : 141,
          "length" : 1
        }
      ]
    }
  ]
}
