{
  "date" : "Thu, 03 Aug, 2023 16:25:31 +0000",
  "doco" : "For each file: start is seconds after start activity occurred. Length = milliseconds activity took",
  "files" : [
    {
      "name" : "/fsh-generated/resources/ImplementationGuide-ans.fhir.fr.agenda.json",
      "size" : 7232,
      "processes" : [
        {
          "activity" : "load",
          "start" : 31,
          "length" : 416
        },
        {
          "activity" : "checkR4R4B",
          "start" : 47,
          "length" : 5
        },
        {
          "activity" : "generateNarratives",
          "start" : 47,
          "length" : 406
        },
        {
          "activity" : "validate",
          "start" : 73,
          "length" : 788
        },
        {
          "activity" : "scanForUsageStats",
          "start" : 74,
          "length" : 1
        },
        {
          "activity" : "generate1",
          "start" : 74,
          "length" : 150
        },
        {
          "activity" : "generate2",
          "start" : 81,
          "length" : 260
        },
        {
          "activity" : "generateValidationPack",
          "start" : 104,
          "length" : 3
        }
      ]
    },
    {
      "name" : "fsh-generated/resources/CapabilityStatement-GAP-GestionnaireAgenda.json",
      "size" : 9866,
      "processes" : [
        {
          "activity" : "loadResources",
          "start" : 28,
          "length" : 30
        },
        {
          "activity" : "load-configure",
          "start" : 29,
          "length" : 1
        },
        {
          "activity" : "loadDepInfo",
          "start" : 29,
          "length" : 1
        },
        {
          "activity" : "loadInfo",
          "start" : 29,
          "length" : 1
        },
        {
          "activity" : "load",
          "start" : 31,
          "length" : 21
        },
        {
          "activity" : "generateNarratives",
          "start" : 47,
          "length" : 36
        },
        {
          "activity" : "validate",
          "start" : 72,
          "length" : 378
        },
        {
          "activity" : "scanForUsageStats",
          "start" : 74,
          "length" : 1
        },
        {
          "activity" : "processProvenanceDetails",
          "start" : 74,
          "length" : 1
        },
        {
          "activity" : "generate1",
          "start" : 74,
          "length" : 32
        },
        {
          "activity" : "generate2",
          "start" : 81,
          "length" : 44
        },
        {
          "activity" : "generateValidationPack",
          "start" : 104,
          "length" : 1
        }
      ]
    },
    {
      "name" : "fsh-generated/resources/SearchParameter-GAP-Appointment-priority.json",
      "size" : 511,
      "processes" : [
        {
          "activity" : "loadResources",
          "start" : 28,
          "length" : 18
        },
        {
          "activity" : "load",
          "start" : 31,
          "length" : 11
        },
        {
          "activity" : "load",
          "start" : 32,
          "length" : 3
        },
        {
          "activity" : "generateNarratives",
          "start" : 47,
          "length" : 13
        },
        {
          "activity" : "validate",
          "start" : 72,
          "length" : 14
        },
        {
          "activity" : "generate1",
          "start" : 74,
          "length" : 5
        },
        {
          "activity" : "generate2",
          "start" : 81,
          "length" : 21
        },
        {
          "activity" : "generateExampleZip",
          "start" : 104,
          "length" : 1
        }
      ]
    },
    {
      "name" : "fsh-generated/resources/CapabilityStatement-GAP-Consommateur.json",
      "size" : 16662,
      "processes" : [
        {
          "activity" : "loadResources",
          "start" : 28,
          "length" : 24
        },
        {
          "activity" : "loadInfo",
          "start" : 29,
          "length" : 2
        },
        {
          "activity" : "load",
          "start" : 31,
          "length" : 20
        },
        {
          "activity" : "checkR4R4B",
          "start" : 47,
          "length" : 1
        },
        {
          "activity" : "generateNarratives",
          "start" : 47,
          "length" : 28
        },
        {
          "activity" : "validate",
          "start" : 73,
          "length" : 94
        },
        {
          "activity" : "generate1",
          "start" : 74,
          "length" : 47
        },
        {
          "activity" : "generate2",
          "start" : 81,
          "length" : 33
        },
        {
          "activity" : "generateValidationPack",
          "start" : 104,
          "length" : 1
        }
      ]
    },
    {
      "name" : "fsh-generated/resources/SearchParameter-GAP-Slot-earliestStart.json",
      "size" : 620,
      "processes" : [
        {
          "activity" : "loadResources",
          "start" : 28,
          "length" : 10
        },
        {
          "activity" : "load",
          "start" : 31,
          "length" : 4
        },
        {
          "activity" : "load",
          "start" : 32,
          "length" : 3
        },
        {
          "activity" : "generateNarratives",
          "start" : 47,
          "length" : 12
        },
        {
          "activity" : "validate",
          "start" : 72,
          "length" : 8
        },
        {
          "activity" : "generate1",
          "start" : 74,
          "length" : 5
        },
        {
          "activity" : "generate2",
          "start" : 81,
          "length" : 20
        }
      ]
    },
    {
      "name" : "fsh-generated/resources/CapabilityStatement-GAP-DeclarantRDV.json",
      "size" : 1635,
      "processes" : [
        {
          "activity" : "loadResources",
          "start" : 28,
          "length" : 11
        },
        {
          "activity" : "load",
          "start" : 31,
          "length" : 4
        },
        {
          "activity" : "checkR4R4B",
          "start" : 47,
          "length" : 1
        },
        {
          "activity" : "generateNarratives",
          "start" : 47,
          "length" : 13
        },
        {
          "activity" : "validate",
          "start" : 73,
          "length" : 9
        },
        {
          "activity" : "generate1",
          "start" : 74,
          "length" : 9
        },
        {
          "activity" : "generate2",
          "start" : 81,
          "length" : 9
        },
        {
          "activity" : "generateValidationPack",
          "start" : 104,
          "length" : 1
        }
      ]
    },
    {
      "name" : "fsh-generated/resources/SearchParameter-GAP-Appointment-created.json",
      "size" : 415,
      "processes" : [
        {
          "activity" : "loadResources",
          "start" : 28,
          "length" : 9
        },
        {
          "activity" : "load",
          "start" : 31,
          "length" : 4
        },
        {
          "activity" : "load",
          "start" : 32,
          "length" : 3
        },
        {
          "activity" : "generateNarratives",
          "start" : 47,
          "length" : 11
        },
        {
          "activity" : "validate",
          "start" : 72,
          "length" : 5
        },
        {
          "activity" : "generate1",
          "start" : 74,
          "length" : 5
        },
        {
          "activity" : "generate2",
          "start" : 81,
          "length" : 20
        }
      ]
    },
    {
      "name" : "fsh-generated/resources/SearchParameter-GAP-Appointment-description.json",
      "size" : 586,
      "processes" : [
        {
          "activity" : "loadResources",
          "start" : 28,
          "length" : 10
        },
        {
          "activity" : "load-configure",
          "start" : 29,
          "length" : 1
        },
        {
          "activity" : "load",
          "start" : 31,
          "length" : 3
        },
        {
          "activity" : "load",
          "start" : 32,
          "length" : 3
        },
        {
          "activity" : "generateNarratives",
          "start" : 47,
          "length" : 12
        },
        {
          "activity" : "validate",
          "start" : 72,
          "length" : 5
        },
        {
          "activity" : "generate1",
          "start" : 74,
          "length" : 5
        },
        {
          "activity" : "generate2",
          "start" : 81,
          "length" : 21
        },
        {
          "activity" : "generateValidationPack",
          "start" : 104,
          "length" : 1
        }
      ]
    },
    {
      "name" : "fsh-generated/resources/StructureDefinition-gap-bundle-reponse-demande-consult-dispo.json",
      "size" : 10802,
      "processes" : [
        {
          "activity" : "loadResources",
          "start" : 28,
          "length" : 702
        },
        {
          "activity" : "scan",
          "start" : 29,
          "length" : 1
        },
        {
          "activity" : "load",
          "start" : 29,
          "length" : 776
        },
        {
          "activity" : "generateSnapshots",
          "start" : 32,
          "length" : 7422
        },
        {
          "activity" : "generateNarratives",
          "start" : 47,
          "length" : 6862
        },
        {
          "activity" : "validate",
          "start" : 62,
          "length" : 7094
        },
        {
          "activity" : "checkConformanceResources",
          "start" : 74,
          "length" : 2
        },
        {
          "activity" : "scanForUsageStats",
          "start" : 74,
          "length" : 5
        },
        {
          "activity" : "generate1",
          "start" : 74,
          "length" : 1910
        },
        {
          "activity" : "generate2",
          "start" : 81,
          "length" : 6599
        },
        {
          "activity" : "generateValidationPack",
          "start" : 104,
          "length" : 56
        },
        {
          "activity" : "scanExamplesForR5",
          "start" : 120,
          "length" : 4
        }
      ]
    },
    {
      "name" : "fsh-generated/resources/SearchParameter-GAP-Appointment-latestStart.json",
      "size" : 652,
      "processes" : [
        {
          "activity" : "loadResources",
          "start" : 29,
          "length" : 10
        },
        {
          "activity" : "load",
          "start" : 31,
          "length" : 3
        },
        {
          "activity" : "load",
          "start" : 32,
          "length" : 3
        },
        {
          "activity" : "generateNarratives",
          "start" : 54,
          "length" : 12
        },
        {
          "activity" : "validate",
          "start" : 72,
          "length" : 9
        },
        {
          "activity" : "generate1",
          "start" : 76,
          "length" : 6
        },
        {
          "activity" : "generate2",
          "start" : 88,
          "length" : 14
        },
        {
          "activity" : "generateValidationPack",
          "start" : 104,
          "length" : 1
        }
      ]
    },
    {
      "name" : "fsh-generated/resources/SearchParameter-GAP-Slot-latestStart.json",
      "size" : 612,
      "processes" : [
        {
          "activity" : "loadResources",
          "start" : 29,
          "length" : 9
        },
        {
          "activity" : "load",
          "start" : 31,
          "length" : 4
        },
        {
          "activity" : "load",
          "start" : 32,
          "length" : 3
        },
        {
          "activity" : "generateNarratives",
          "start" : 54,
          "length" : 11
        },
        {
          "activity" : "validate",
          "start" : 72,
          "length" : 7
        },
        {
          "activity" : "checkURLsUnique",
          "start" : 74,
          "length" : 1
        },
        {
          "activity" : "generate1",
          "start" : 76,
          "length" : 5
        },
        {
          "activity" : "generate2",
          "start" : 88,
          "length" : 12
        }
      ]
    },
    {
      "name" : "fsh-generated/resources/StructureDefinition-gap-bundle-reponse-demande-consult-rdv.json",
      "size" : 11405,
      "processes" : [
        {
          "activity" : "loadResources",
          "start" : 29,
          "length" : 794
        },
        {
          "activity" : "load",
          "start" : 30,
          "length" : 807
        },
        {
          "activity" : "generateSnapshots",
          "start" : 39,
          "length" : 7690
        },
        {
          "activity" : "generateNarratives",
          "start" : 54,
          "length" : 7398
        },
        {
          "activity" : "validate",
          "start" : 69,
          "length" : 3716
        },
        {
          "activity" : "checkConformanceResources",
          "start" : 74,
          "length" : 1
        },
        {
          "activity" : "scanForUsageStats",
          "start" : 74,
          "length" : 4
        },
        {
          "activity" : "generate1",
          "start" : 76,
          "length" : 2010
        },
        {
          "activity" : "generate2",
          "start" : 88,
          "length" : 4615
        },
        {
          "activity" : "generateValidationPack",
          "start" : 104,
          "length" : 47
        },
        {
          "activity" : "scanExamplesForR5",
          "start" : 120,
          "length" : 3
        }
      ]
    },
    {
      "name" : "fsh-generated/resources/CapabilityStatement-Gap-Declarant.json",
      "size" : 5037,
      "processes" : [
        {
          "activity" : "loadResources",
          "start" : 29,
          "length" : 8
        },
        {
          "activity" : "load",
          "start" : 31,
          "length" : 9
        },
        {
          "activity" : "generateNarratives",
          "start" : 61,
          "length" : 18
        },
        {
          "activity" : "validate",
          "start" : 73,
          "length" : 23
        },
        {
          "activity" : "generate1",
          "start" : 78,
          "length" : 23
        },
        {
          "activity" : "generate2",
          "start" : 92,
          "length" : 12
        },
        {
          "activity" : "generateValidationPack",
          "start" : 104,
          "length" : 1
        }
      ]
    },
    {
      "name" : "fsh-generated/resources/CapabilityStatement-GAP-GestionnaireRessources.json",
      "size" : 4121,
      "processes" : [
        {
          "activity" : "loadResources",
          "start" : 29,
          "length" : 7
        },
        {
          "activity" : "load",
          "start" : 31,
          "length" : 8
        },
        {
          "activity" : "checkR4R4B",
          "start" : 47,
          "length" : 1
        },
        {
          "activity" : "generateNarratives",
          "start" : 62,
          "length" : 17
        },
        {
          "activity" : "validate",
          "start" : 73,
          "length" : 20
        },
        {
          "activity" : "generate1",
          "start" : 78,
          "length" : 18
        },
        {
          "activity" : "generate2",
          "start" : 92,
          "length" : 12
        },
        {
          "activity" : "generateValidationPack",
          "start" : 104,
          "length" : 1
        }
      ]
    },
    {
      "name" : "fsh-generated/resources/SearchParameter-GAP-Appointment-earliestStart.json",
      "size" : 680,
      "processes" : [
        {
          "activity" : "loadResources",
          "start" : 29,
          "length" : 2
        },
        {
          "activity" : "load",
          "start" : 31,
          "length" : 3
        },
        {
          "activity" : "load",
          "start" : 32,
          "length" : 3
        },
        {
          "activity" : "generateNarratives",
          "start" : 62,
          "length" : 12
        },
        {
          "activity" : "validate",
          "start" : 72,
          "length" : 8
        },
        {
          "activity" : "generate1",
          "start" : 78,
          "length" : 5
        },
        {
          "activity" : "generate2",
          "start" : 92,
          "length" : 8
        }
      ]
    }
  ]
}
